pitsu/__init__.py
pitsu/element/__init__.py
pitsu/element/_base.py
pitsu/element/classes.py
pitsu-1.2.3.dist-info/LICENSE
pitsu-1.2.3.dist-info/METADATA
pitsu-1.2.3.dist-info/WHEEL
pitsu-1.2.3.dist-info/top_level.txt
pitsu-1.2.3.dist-info/RECORD
