Metadata-Version: 2.1
Name: pitsu
Version: 1.2.3
Summary: a python module to create html pages with python code
Author: Filipi565
Project-URL: Source, https://github.com/Filipi565/pitsu
Project-URL: Issues, https://github.com/Filipi565/pitsu/issues
Project-URL: Documentation, https://github.com/Filipi565/pitsu/blob/main/Docs.md
Classifier: Programming Language :: Python :: 3
Classifier: License :: OSI Approved :: MIT License
Classifier: Operating System :: OS Independent
Requires-Python: >=3.8
License-File: LICENSE
